odoo8_addon_account_tax_chart_interval-8.0.1.0.0.99.dev11-py2.7-nspkg.pth
odoo8_addon_account_tax_chart_interval-8.0.1.0.0.99.dev11.dist-info/DESCRIPTION.rst
odoo8_addon_account_tax_chart_interval-8.0.1.0.0.99.dev11.dist-info/METADATA
odoo8_addon_account_tax_chart_interval-8.0.1.0.0.99.dev11.dist-info/RECORD
odoo8_addon_account_tax_chart_interval-8.0.1.0.0.99.dev11.dist-info/WHEEL
odoo8_addon_account_tax_chart_interval-8.0.1.0.0.99.dev11.dist-info/metadata.json
odoo8_addon_account_tax_chart_interval-8.0.1.0.0.99.dev11.dist-info/namespace_packages.txt
odoo8_addon_account_tax_chart_interval-8.0.1.0.0.99.dev11.dist-info/top_level.txt
odoo_addons/account_tax_chart_interval/README.rst
odoo_addons/account_tax_chart_interval/__init__.py
odoo_addons/account_tax_chart_interval/__openerp__.py
odoo_addons/account_tax_chart_interval/i18n/account_tax_chart_interval.pot
odoo_addons/account_tax_chart_interval/i18n/de.po
odoo_addons/account_tax_chart_interval/i18n/es.po
odoo_addons/account_tax_chart_interval/i18n/es_ES.po
odoo_addons/account_tax_chart_interval/i18n/es_MX.po
odoo_addons/account_tax_chart_interval/i18n/fr.po
odoo_addons/account_tax_chart_interval/i18n/hr.po
odoo_addons/account_tax_chart_interval/i18n/sl.po
odoo_addons/account_tax_chart_interval/models/__init__.py
odoo_addons/account_tax_chart_interval/models/account_tax_code.py
odoo_addons/account_tax_chart_interval/static/description/icon.png
odoo_addons/account_tax_chart_interval/wizard/__init__.py
odoo_addons/account_tax_chart_interval/wizard/account_tax_chart.py
odoo_addons/account_tax_chart_interval/wizard/account_tax_chart_view.xml
